pyTON/__init__.py
pyTON/__main__.py
pyTON/address_utils.py
pyTON/client.py
pyTON/tonlibjson.py
pyTON/utils.py
pyTON/wallet_utils.py
pyTON/distlib/darwin/libtonlibjson.dylib
pyTON/distlib/linux/libtonlibjson.so
pyTON/webserver/__init__.py
pyTON/webserver/application.css
pyTON/webserver/application.js
pyTON/webserver/index.html
pyTON-0.1.4.dist-info/METADATA
pyTON-0.1.4.dist-info/WHEEL
pyTON-0.1.4.dist-info/top_level.txt
pyTON-0.1.4.dist-info/zip-safe
pyTON-0.1.4.dist-info/RECORD
