Metadata-Version: 2.1
Name: pyTON
Version: 0.1.4
Summary: Python API for libtonlibjson (Telegram Open Network Light Client)
Home-page: https://github.com/viewst/pyTON
Author: Emelyanenko Kirill
License: UNKNOWN
Platform: UNKNOWN
Classifier: Development Status :: 3 - Alpha
Classifier: Intended Audience :: Developers
Classifier: Programming Language :: Python :: 3.7
Classifier: License :: Other/Proprietary License
Classifier: Topic :: Software Development :: Libraries
Requires-Python: >=3.7
Requires-Dist: aiohttp (>=3)
Requires-Dist: crc16
Requires-Dist: ed25519 (~=1.5)
Requires-Dist: mnemonic
Requires-Dist: pycryptodome
Requires-Dist: pynacl
Requires-Dist: tvm-valuetypes
Requires-Dist: ujson (>=1.35)
Requires-Dist: uvloop
